LICENSE.md
MANIFEST.in
README.md
setup.cfg
setup.py
docs/source/changelog.rst
docs/source/conf.py
docs/source/configuration.rst
docs/source/index.rst
docs/source/installation.rst
docs/source/license.rst
docs/source/prerequisites.rst
docs/source/templates.rst
sizeof_django_tellafriend.egg-info/PKG-INFO
sizeof_django_tellafriend.egg-info/SOURCES.txt
sizeof_django_tellafriend.egg-info/dependency_links.txt
sizeof_django_tellafriend.egg-info/not-zip-safe
sizeof_django_tellafriend.egg-info/requires.txt
sizeof_django_tellafriend.egg-info/top_level.txt
tellafriend/__init__.py
tellafriend/admin.py
tellafriend/forms.py
tellafriend/models.py
tellafriend/urls.py
tellafriend/views.py
tellafriend/locale/de/LC_MESSAGES/django.mo
tellafriend/locale/de/LC_MESSAGES/django.po
tellafriend/locale/pl/LC_MESSAGES/django.mo
tellafriend/locale/pl/LC_MESSAGES/django.po
tellafriend/migrations/0001_initial.py
tellafriend/migrations/__init__.py
tellafriend/south_migrations/0001_initial.py
tellafriend/south_migrations/__init__.py
tellafriend/templates/tellafriend/email.html
tellafriend/templates/tellafriend/email.txt
tellafriend/templates/tellafriend/success.html
tellafriend/templates/tellafriend/tellafriend.html