Metadata-Version: 1.0
Name: sizeof-django-tellafriend
Version: 0.1.3
Summary: SIZEOF.PL | Django Tell a Friend
Home-page: https://bitbucket.org/sizeof/sizeof-django-tellafriend/
Author: SIZEOF.PL | Mariusz Smenżyk
Author-email: mariusz@sizeof.pl
License: MIT
Keywords: django tellafriend recommend
Platform: UNKNOWN
